{
  "hash": "c3439bfd",
  "configHash": "751767f2",
  "lockfileHash": "447404c9",
  "browserHash": "7a7bd438",
  "optimized": {
    "vue": {
      "src": "../../../node_modules/vue/dist/vue.runtime.esm-bundler.js",
      "file": "vue.js",
      "fileHash": "f57ffc73",
      "needsInterop": false
    },
    "vitepress > @vue/devtools-api": {
      "src": "../../../node_modules/@vue/devtools-api/dist/index.js",
      "file": "vitepress___@vue_devtools-api.js",
      "fileHash": "ab425a10",
      "needsInterop": false
    },
    "vitepress > @vueuse/core": {
      "src": "../../../node_modules/@vueuse/core/index.mjs",
      "file": "vitepress___@vueuse_core.js",
      "fileHash": "babbc924",
      "needsInterop": false
    },
    "primevue/config": {
      "src": "../../../node_modules/primevue/config/index.mjs",
      "file": "primevue_config.js",
      "fileHash": "db57b961",
      "needsInterop": false
    },
    "primevue/button": {
      "src": "../../../node_modules/primevue/button/index.mjs",
      "file": "primevue_button.js",
      "fileHash": "77e60f3d",
      "needsInterop": false
    },
    "@primevue/themes/aura": {
      "src": "../../../node_modules/@primevue/themes/aura/index.mjs",
      "file": "@primevue_themes_aura.js",
      "fileHash": "411de595",
      "needsInterop": false
    },
    "primevue/card": {
      "src": "../../../node_modules/primevue/card/index.mjs",
      "file": "primevue_card.js",
      "fileHash": "40e5d5fa",
      "needsInterop": false
    },
    "primevue/tabs": {
      "src": "../../../node_modules/primevue/tabs/index.mjs",
      "file": "primevue_tabs.js",
      "fileHash": "8fc5dae7",
      "needsInterop": false
    },
    "primevue/tablist": {
      "src": "../../../node_modules/primevue/tablist/index.mjs",
      "file": "primevue_tablist.js",
      "fileHash": "17420385",
      "needsInterop": false
    },
    "primevue/tab": {
      "src": "../../../node_modules/primevue/tab/index.mjs",
      "file": "primevue_tab.js",
      "fileHash": "e7de4781",
      "needsInterop": false
    },
    "primevue/tabpanels": {
      "src": "../../../node_modules/primevue/tabpanels/index.mjs",
      "file": "primevue_tabpanels.js",
      "fileHash": "a505a62d",
      "needsInterop": false
    },
    "primevue/tabpanel": {
      "src": "../../../node_modules/primevue/tabpanel/index.mjs",
      "file": "primevue_tabpanel.js",
      "fileHash": "9f2628e0",
      "needsInterop": false
    },
    "primevue/divider": {
      "src": "../../../node_modules/primevue/divider/index.mjs",
      "file": "primevue_divider.js",
      "fileHash": "a7ef4f6f",
      "needsInterop": false
    },
    "primevue/imagecompare": {
      "src": "../../../node_modules/primevue/imagecompare/index.mjs",
      "file": "primevue_imagecompare.js",
      "fileHash": "cd8a14bf",
      "needsInterop": false
    },
    "primevue/fieldset": {
      "src": "../../../node_modules/primevue/fieldset/index.mjs",
      "file": "primevue_fieldset.js",
      "fileHash": "f2636ffe",
      "needsInterop": false
    },
    "primevue/galleria": {
      "src": "../../../node_modules/primevue/galleria/index.mjs",
      "file": "primevue_galleria.js",
      "fileHash": "9ad5f194",
      "needsInterop": false
    }
  },
  "chunks": {
    "chunk-SUZXZJMW": {
      "file": "chunk-SUZXZJMW.js"
    },
    "chunk-KI4UNW25": {
      "file": "chunk-KI4UNW25.js"
    },
    "chunk-BATNEY45": {
      "file": "chunk-BATNEY45.js"
    },
    "chunk-IZV5ZA7Q": {
      "file": "chunk-IZV5ZA7Q.js"
    },
    "chunk-LAYGNASV": {
      "file": "chunk-LAYGNASV.js"
    },
    "chunk-M3Z2YNOL": {
      "file": "chunk-M3Z2YNOL.js"
    },
    "chunk-6LRDN5RD": {
      "file": "chunk-6LRDN5RD.js"
    },
    "chunk-ATOVSKCZ": {
      "file": "chunk-ATOVSKCZ.js"
    },
    "chunk-5J2UBCUN": {
      "file": "chunk-5J2UBCUN.js"
    }
  }
}